pycobaltix/__init__.py
pycobaltix/address/__init__.py
pycobaltix/address/convert_coordinate.py
pycobaltix/address/endpoint.py
pycobaltix/address/model.py
pycobaltix/address/naver_api.py
pycobaltix/public/__init__.py
pycobaltix/public/data/__init__.py
pycobaltix/public/data/endpoints.py
pycobaltix/public/data/getBrExposPubuseAreaInfo.py
pycobaltix/public/data/getBrTitleInfo.py
pycobaltix/public/juso/__init__.py
pycobaltix/public/juso/endpoints.py
pycobaltix/public/juso/model.py
pycobaltix/public/registration/__init__.py
pycobaltix/public/registration/check.py
pycobaltix/public/registration/pdf_parsing.py
pycobaltix/public/registration/registration.py
pycobaltix/public/vworld/__init__.py
pycobaltix/public/vworld/endpoints.py
pycobaltix/public/vworld/response_format.py
pycobaltix/public/vworld/response/__init__.py
pycobaltix/public/vworld/response/buldSnList.py
pycobaltix/public/vworld/response/indvdLandPrice.py
pycobaltix/public/vworld/response/ladfrlList.py
pycobaltix/schemas/__init__.py
pycobaltix/schemas/responses.py
pycobaltix/slack/__init__.py
pycobaltix/slack/async_slack_web_hook.py
pycobaltix/slack/slack_web_hook.py
pycobaltix-0.4.2.dist-info/METADATA
pycobaltix-0.4.2.dist-info/WHEEL
pycobaltix-0.4.2.dist-info/RECORD
