Metadata-Version: 2.4
Name: pycobaltix
Version: 0.4.2
Summary: 코발틱스 파이썬 유틸리티 패키지
Project-URL: Homepage, https://github.com/KAIS-Inc/pycobaltix
Project-URL: Bug Tracker, https://github.com/KAIS-Inc/pycobaltix/issues
Author-email: steven <steven@cobaltix.io>
License: MIT
Classifier: License :: OSI Approved :: MIT License
Classifier: Operating System :: OS Independent
Classifier: Programming Language :: Python :: 3
Requires-Python: >=3.12
Requires-Dist: aiohttp>=3.12.9
Requires-Dist: httpx>=0.28.1
Requires-Dist: pydantic>=2.0.0
Requires-Dist: slack-sdk>=3.35.0
Requires-Dist: typing-extensions>=4.0.0
Provides-Extra: all
Requires-Dist: dotenv>=0.9.9; extra == 'all'
Requires-Dist: pdfplumber>=0.11.7; extra == 'all'
Requires-Dist: pyproj>=3.7.1; extra == 'all'
Requires-Dist: tenacity>=9.1.2; extra == 'all'
Provides-Extra: dev
Requires-Dist: bandit>=1.7.0; extra == 'dev'
Requires-Dist: black>=23.0.0; extra == 'dev'
Requires-Dist: isort>=5.0.0; extra == 'dev'
Requires-Dist: mypy>=1.16.0; extra == 'dev'
Requires-Dist: pytest-asyncio>=0.21.0; extra == 'dev'
Requires-Dist: pytest-cov>=4.0.0; extra == 'dev'
Requires-Dist: pytest-mock>=3.10.0; extra == 'dev'
Requires-Dist: pytest-watch>=4.2.0; extra == 'dev'
Requires-Dist: pytest>=7.0.0; extra == 'dev'
Requires-Dist: ruff>=0.12.2; extra == 'dev'
Requires-Dist: safety>=2.0.0; extra == 'dev'
Requires-Dist: tox>=4.0.0; extra == 'dev'
